{"sports_content":{"sports_meta":{"date_time":"20150402 1343","season_meta":{"calendar_date":"20150402","season_year":"2014","stats_season_year":"2014","stats_season_id":"22014","stats_season_stage":"2","roster_season_year":"2014","schedule_season_year":"2014","standings_season_year":"2014","season_id":"22014","display_year":"2014-15","display_season":"Regular Season","season_stage":"2"},"next":{"url":"http:\/\/data.nba.com\/data\/10s\/json\/cms\/noseason\/game\/20150325\/0021401062\/pbp_2.json"}},"game":{"id":"0021401062","game_url":"20150325\/ATLORL","season_id":"22014","date":"20150325","time":"1900","arena":"Amway Center","city":"Orlando","state":"FL","country":"","home_start_date":"20150325","home_start_time":"1900","visitor_start_date":"20150325","visitor_start_time":"1900","isLeaguePass":"1","previewAvailable":"1","recapAvailable":"1","notebookAvailable":"0","play":[{"event":"117","clock":"","description":"Start Period","home_score":"31","visitor_score":"23","team_abr":""},{"event":"118","clock":"11:45","description":"[ORL 33-23] Nicholson Jump Shot: Made (2 PTS) Assist: Green (1 AST)","home_score":"33","visitor_score":"23","team_abr":"ORL"},{"event":"119","clock":"11:25","description":"[ATL] Schroder Jump Shot: Missed Block: Ridnour (1 BLK)","home_score":"33","visitor_score":"23","team_abr":"ATL"},{"event":"120","clock":"11:22","description":"[ATL] Schroder Rebound (Off:1 Def:0)","home_score":"33","visitor_score":"23","team_abr":"ATL"},{"event":"121","clock":"11:18","description":"[ATL] Schroder Pullup Jump shot: Missed","home_score":"33","visitor_score":"23","team_abr":"ATL"},{"event":"122","clock":"11:17","description":"[ORL] Gordon Rebound (Off:0 Def:1)","home_score":"33","visitor_score":"23","team_abr":"ORL"},{"event":"123","clock":"10:56","description":"[ORL] Frye Hook Shot: Missed Block: Horford (1 BLK)","home_score":"33","visitor_score":"23","team_abr":"ORL"},{"event":"124","clock":"10:54","description":"[ATL] Horford Rebound (Off:1 Def:2)","home_score":"33","visitor_score":"23","team_abr":"ATL"},{"event":"125","clock":"10:48","description":"[ATL] Sefolosha Foul: Offensive Charge (1 PF)","home_score":"33","visitor_score":"23","team_abr":"ATL"},{"event":"126","clock":"10:48","description":"[ATL] Sefolosha Turnover : Foul (1 TO)","home_score":"33","visitor_score":"23","team_abr":"ATL"},{"event":"127","clock":"10:36","description":"[ORL] Ridnour Jump Shot: Missed","home_score":"33","visitor_score":"23","team_abr":"ORL"},{"event":"128","clock":"10:35","description":"[ATL] Antic Rebound (Off:0 Def:2)","home_score":"33","visitor_score":"23","team_abr":"ATL"},{"event":"129","clock":"10:26","description":"[ATL 26-33] Korver 3pt Shot: Made (6 PTS) Assist: Horford (2 AST)","home_score":"33","visitor_score":"26","team_abr":"ATL"},{"event":"130","clock":"10:03","description":"[ORL 35-26] Nicholson Hook Shot: Made (4 PTS) Assist: Gordon (1 AST)","home_score":"35","visitor_score":"26","team_abr":"ORL"},{"event":"131","clock":"09:48","description":"[ATL] Korver 3pt Shot: Missed","home_score":"35","visitor_score":"26","team_abr":"ATL"},{"event":"132","clock":"09:46","description":"[ATL] Horford Rebound (Off:2 Def:2)","home_score":"35","visitor_score":"26","team_abr":"ATL"},{"event":"133","clock":"09:44","description":"[ATL] Korver 3pt Shot: Missed","home_score":"35","visitor_score":"26","team_abr":"ATL"},{"event":"134","clock":"09:42","description":"[ORL] Frye Rebound (Off:0 Def:1)","home_score":"35","visitor_score":"26","team_abr":"ORL"},{"event":"135","clock":"09:29","description":"[ORL] Green Pullup Jump shot: Missed","home_score":"35","visitor_score":"26","team_abr":"ORL"},{"event":"136","clock":"09:28","description":"[ATL] Horford Rebound (Off:2 Def:3)","home_score":"35","visitor_score":"26","team_abr":"ATL"},{"event":"137","clock":"09:16","description":"[ATL] Schroder 3pt Shot: Missed","home_score":"35","visitor_score":"26","team_abr":"ATL"},{"event":"138","clock":"09:14","description":"[ORL] Gordon Rebound (Off:0 Def:2)","home_score":"35","visitor_score":"26","team_abr":"ORL"},{"event":"139","clock":"09:06","description":"[ORL] Ridnour 3pt Shot: Missed","home_score":"35","visitor_score":"26","team_abr":"ORL"},{"event":"140","clock":"09:05","description":"[ATL] Korver Rebound (Off:0 Def:3)","home_score":"35","visitor_score":"26","team_abr":"ATL"},{"event":"141","clock":"08:57","description":"[ATL] Horford Turnover : Lost Ball (2 TO) Steal:Gordon (1 ST)","home_score":"35","visitor_score":"26","team_abr":"ATL"},{"event":"142","clock":"08:45","description":"[ATL] Antic Foul: Shooting (2 PF) (2 FTA)","home_score":"35","visitor_score":"26","team_abr":"ATL"},{"event":"143","clock":"08:45","description":"Timeout : Official","home_score":"35","visitor_score":"26","team_abr":""},{"event":"145","clock":"08:45","description":"[ATL] Antic Substitution replaced by Brand","home_score":"35","visitor_score":"26","team_abr":"ATL"},{"event":"146","clock":"08:45","description":"[ATL] Schroder Substitution replaced by Teague","home_score":"35","visitor_score":"26","team_abr":"ATL"},{"event":"148","clock":"08:45","description":"[ORL 36-26] Nicholson Free Throw 1 of 2 (5 PTS)","home_score":"36","visitor_score":"26","team_abr":"ORL"},{"event":"150","clock":"08:45","description":"[ORL 37-26] Nicholson Free Throw 2 of 2 (6 PTS)","home_score":"37","visitor_score":"26","team_abr":"ORL"},{"event":"152","clock":"08:27","description":"[ATL] Brand Jump Shot: Missed","home_score":"37","visitor_score":"26","team_abr":"ATL"},{"event":"153","clock":"08:26","description":"[ORL] Ridnour Rebound (Off:0 Def:1)","home_score":"37","visitor_score":"26","team_abr":"ORL"},{"event":"154","clock":"08:12","description":"[ORL] Nicholson Jump Shot: Missed","home_score":"37","visitor_score":"26","team_abr":"ORL"},{"event":"155","clock":"08:10","description":"[ATL] Teague Rebound (Off:0 Def:1)","home_score":"37","visitor_score":"26","team_abr":"ATL"},{"event":"156","clock":"08:02","description":"[ORL] Gordon Foul: Personal (1 PF)","home_score":"37","visitor_score":"26","team_abr":"ORL"},{"event":"157","clock":"08:02","description":"[ATL] Sefolosha Substitution replaced by Schroder","home_score":"37","visitor_score":"26","team_abr":"ATL"},{"event":"158","clock":"07:46","description":"[ATL] Horford Jump Shot: Missed","home_score":"37","visitor_score":"26","team_abr":"ATL"},{"event":"159","clock":"07:45","description":"[ORL] Green Rebound (Off:0 Def:1)","home_score":"37","visitor_score":"26","team_abr":"ORL"},{"event":"160","clock":"07:37","description":"[ORL 39-26] Green Driving Layup Shot: Made (5 PTS)","home_score":"39","visitor_score":"26","team_abr":"ORL"},{"event":"161","clock":"07:28","description":"[ATL 28-39] Schroder Driving Layup Shot: Made (3 PTS)","home_score":"39","visitor_score":"28","team_abr":"ATL"},{"event":"162","clock":"07:20","description":"[ORL] Nicholson 3pt Shot: Missed","home_score":"39","visitor_score":"28","team_abr":"ORL"},{"event":"163","clock":"07:18","description":"[ORL 41-28] Frye Tip Shot: Made (2 PTS)","home_score":"41","visitor_score":"28","team_abr":"ORL"},{"event":"164","clock":"07:18","description":"[ORL] Frye Rebound (Off:1 Def:1)","home_score":"39","visitor_score":"28","team_abr":"ORL"},{"event":"165","clock":"07:11","description":"[ATL] Teague Driving Reverse Layup Shot: Missed","home_score":"41","visitor_score":"28","team_abr":"ATL"},{"event":"166","clock":"07:10","description":"[ATL] Team Rebound","home_score":"41","visitor_score":"28","team_abr":"ATL"},{"event":"167","clock":"07:04","description":"[ATL] Korver Turnaround Jump Shot: Missed","home_score":"41","visitor_score":"28","team_abr":"ATL"},{"event":"168","clock":"07:02","description":"[ORL] Gordon Rebound (Off:0 Def:3)","home_score":"41","visitor_score":"28","team_abr":"ORL"},{"event":"169","clock":"06:55","description":"[ORL] Frye 3pt Shot: Missed","home_score":"41","visitor_score":"28","team_abr":"ORL"},{"event":"170","clock":"06:54","description":"[ATL] Korver Rebound (Off:0 Def:4)","home_score":"41","visitor_score":"28","team_abr":"ATL"},{"event":"171","clock":"06:38","description":"[ATL] Horford Hook Shot: Missed Block: Nicholson (1 BLK)","home_score":"41","visitor_score":"28","team_abr":"ATL"},{"event":"172","clock":"06:38","description":"[ORL] Team Rebound","home_score":"41","visitor_score":"28","team_abr":"ORL"},{"event":"173","clock":"06:38","description":"[ATL] Korver Substitution replaced by Carroll","home_score":"41","visitor_score":"28","team_abr":"ATL"},{"event":"174","clock":"06:25","description":"[ORL] Gordon 3pt Shot: Missed","home_score":"41","visitor_score":"28","team_abr":"ORL"},{"event":"175","clock":"06:23","description":"[ATL] Carroll Rebound (Off:0 Def:2)","home_score":"41","visitor_score":"28","team_abr":"ATL"},{"event":"176","clock":"06:05","description":"[ATL] Schroder Turnover : Bad Pass (2 TO)","home_score":"41","visitor_score":"28","team_abr":"ATL"},{"event":"177","clock":"06:05","description":"[ATL] Horford Substitution replaced by Millsap","home_score":"41","visitor_score":"28","team_abr":"ATL"},{"event":"178","clock":"05:53","description":"[ORL] Nicholson Turnover : Bad Pass (1 TO) Steal:Carroll (1 ST)","home_score":"41","visitor_score":"28","team_abr":"ORL"},{"event":"179","clock":"05:49","description":"[ATL 30-41] Carroll Driving Dunk Shot: Made (4 PTS)","home_score":"41","visitor_score":"30","team_abr":"ATL"},{"event":"180","clock":"05:49","description":"[ORL] Team Timeout : Regular","home_score":"41","visitor_score":"30","team_abr":"ORL"},{"event":"184","clock":"05:49","description":"[ORL] Green Substitution replaced by Harris","home_score":"41","visitor_score":"30","team_abr":"ORL"},{"event":"185","clock":"05:49","description":"[ORL] Ridnour Substitution replaced by Payton","home_score":"41","visitor_score":"30","team_abr":"ORL"},{"event":"186","clock":"05:49","description":"[ORL] Gordon Substitution replaced by Oladipo","home_score":"41","visitor_score":"30","team_abr":"ORL"},{"event":"187","clock":"05:49","description":"[ORL] Frye Substitution replaced by Dedmon","home_score":"41","visitor_score":"30","team_abr":"ORL"},{"event":"188","clock":"05:49","description":"[ORL] Nicholson Substitution replaced by Vucevic","home_score":"41","visitor_score":"30","team_abr":"ORL"},{"event":"189","clock":"05:42","description":"[ATL] Brand Foul: Personal (1 PF)","home_score":"41","visitor_score":"30","team_abr":"ATL"},{"event":"190","clock":"05:29","description":"[ORL 43-30] Vucevic Hook Shot: Made (8 PTS)","home_score":"43","visitor_score":"30","team_abr":"ORL"},{"event":"191","clock":"05:09","description":"[ATL] Millsap Jump Shot: Missed Block: Dedmon (1 BLK)","home_score":"43","visitor_score":"30","team_abr":"ATL"},{"event":"192","clock":"05:07","description":"[ATL] Millsap Rebound (Off:4 Def:2)","home_score":"43","visitor_score":"30","team_abr":"ATL"},{"event":"193","clock":"05:05","description":"[ATL] Schroder 3pt Shot: Missed","home_score":"43","visitor_score":"30","team_abr":"ATL"},{"event":"194","clock":"05:02","description":"[ATL] Carroll Rebound (Off:1 Def:2)","home_score":"43","visitor_score":"30","team_abr":"ATL"},{"event":"195","clock":"04:55","description":"[ATL 32-43] Carroll Driving Layup Shot: Made (6 PTS) Assist: Schroder (1 AST)","home_score":"43","visitor_score":"32","team_abr":"ATL"},{"event":"196","clock":"04:55","description":"[ORL] Harris Foul: Shooting (1 PF) (1 FTA)","home_score":"43","visitor_score":"32","team_abr":"ORL"},{"event":"197","clock":"04:55","description":"[ATL] Carroll Free Throw 1 of 1 Missed","home_score":"43","visitor_score":"32","team_abr":"ATL"},{"event":"199","clock":"04:52","description":"[ORL] Vucevic Rebound (Off:0 Def:3)","home_score":"43","visitor_score":"32","team_abr":"ORL"},{"event":"200","clock":"04:43","description":"[ORL 45-32] Payton Driving Layup Shot: Made (6 PTS)","home_score":"45","visitor_score":"32","team_abr":"ORL"},{"event":"201","clock":"04:28","description":"[ORL] Vucevic Foul: Shooting (1 PF) (2 FTA)","home_score":"45","visitor_score":"32","team_abr":"ORL"},{"event":"202","clock":"04:28","description":"[ATL] Carroll Free Throw 1 of 2 Missed","home_score":"45","visitor_score":"32","team_abr":"ATL"},{"event":"203","clock":"04:28","description":"[ATL] Team Rebound","home_score":"45","visitor_score":"32","team_abr":"ATL"},{"event":"204","clock":"04:28","description":"[ATL] Schroder Substitution replaced by Korver","home_score":"45","visitor_score":"32","team_abr":"ATL"},{"event":"205","clock":"04:28","description":"[ATL 33-45] Carroll Free Throw 2 of 2 (7 PTS)","home_score":"45","visitor_score":"33","team_abr":"ATL"},{"event":"208","clock":"04:07","description":"[ORL] Payton Layup Shot: Missed Block: Millsap (2 BLK)","home_score":"45","visitor_score":"33","team_abr":"ORL"},{"event":"209","clock":"04:05","description":"[ATL] Carroll Rebound (Off:1 Def:3)","home_score":"45","visitor_score":"33","team_abr":"ATL"},{"event":"210","clock":"03:52","description":"[ATL 35-45] Teague Driving Layup Shot: Made (5 PTS)","home_score":"45","visitor_score":"35","team_abr":"ATL"},{"event":"211","clock":"03:36","description":"[ORL 47-35] Vucevic Jump Shot: Made (10 PTS) Assist: Oladipo (2 AST)","home_score":"47","visitor_score":"35","team_abr":"ORL"},{"event":"212","clock":"03:25","description":"[ATL 38-47] Millsap 3pt Shot: Made (13 PTS) Assist: Teague (2 AST)","home_score":"47","visitor_score":"38","team_abr":"ATL"},{"event":"213","clock":"03:11","description":"[ORL 49-38] Harris Running Jump Shot: Made (9 PTS) Assist: Vucevic (3 AST)","home_score":"49","visitor_score":"38","team_abr":"ORL"},{"event":"214","clock":"02:57","description":"[ATL] Millsap 3pt Shot: Missed","home_score":"49","visitor_score":"38","team_abr":"ATL"},{"event":"215","clock":"02:56","description":"[ORL] Team Rebound","home_score":"49","visitor_score":"38","team_abr":"ORL"},{"event":"216","clock":"02:56","description":"[ATL] Team Timeout : Regular","home_score":"49","visitor_score":"38","team_abr":"ATL"},{"event":"220","clock":"02:56","description":"[ATL] Brand Substitution replaced by Horford","home_score":"49","visitor_score":"38","team_abr":"ATL"},{"event":"222","clock":"02:43","description":"[ORL] Harris Jump Shot: Missed","home_score":"49","visitor_score":"38","team_abr":"ORL"},{"event":"223","clock":"02:42","description":"[ORL] Dedmon Rebound (Off:1 Def:2)","home_score":"49","visitor_score":"38","team_abr":"ORL"},{"event":"224","clock":"02:38","description":"[ORL] Dedmon Layup Shot: Missed","home_score":"49","visitor_score":"38","team_abr":"ORL"},{"event":"225","clock":"02:37","description":"[ORL] Vucevic Tip Shot: Missed","home_score":"49","visitor_score":"38","team_abr":"ORL"},{"event":"226","clock":"02:37","description":"[ORL] Vucevic Rebound (Off:1 Def:3)","home_score":"49","visitor_score":"38","team_abr":"ORL"},{"event":"227","clock":"02:35","description":"[ATL] Korver Rebound (Off:0 Def:5)","home_score":"49","visitor_score":"38","team_abr":"ATL"},{"event":"228","clock":"02:12","description":"[ORL] Payton Foul: Shooting (3 PF) (3 FTA)","home_score":"49","visitor_score":"38","team_abr":"ORL"},{"event":"229","clock":"02:36","description":"[ORL] Vucevic Rebound (Off:2 Def:3)","home_score":"49","visitor_score":"38","team_abr":"ORL"},{"event":"231","clock":"02:36","description":"[ORL] Vucevic Tip Shot: Missed","home_score":"49","visitor_score":"38","team_abr":"ORL"},{"event":"233","clock":"02:12","description":"[ATL 39-49] Millsap Free Throw 1 of 3 (14 PTS)","home_score":"49","visitor_score":"39","team_abr":"ATL"},{"event":"235","clock":"02:12","description":"[ATL 40-49] Millsap Free Throw 2 of 3 (15 PTS)","home_score":"49","visitor_score":"40","team_abr":"ATL"},{"event":"237","clock":"02:12","description":"[ORL] Payton Substitution replaced by Ridnour","home_score":"49","visitor_score":"40","team_abr":"ORL"},{"event":"238","clock":"02:12","description":"[ATL 41-49] Millsap Free Throw 3 of 3 (16 PTS)","home_score":"49","visitor_score":"41","team_abr":"ATL"},{"event":"241","clock":"01:52","description":"[ORL 51-41] Oladipo Step Back Jump shot: Made (13 PTS)","home_score":"51","visitor_score":"41","team_abr":"ORL"},{"event":"242","clock":"01:38","description":"[ATL 43-51] Horford Jump Shot: Made (4 PTS)","home_score":"51","visitor_score":"43","team_abr":"ATL"},{"event":"243","clock":"01:27","description":"[ORL] Ridnour Turnover : Bad Pass (1 TO) Steal:Millsap (1 ST)","home_score":"51","visitor_score":"43","team_abr":"ORL"},{"event":"244","clock":"01:22","description":"[ATL] Carroll Layup Shot: Missed","home_score":"51","visitor_score":"43","team_abr":"ATL"},{"event":"245","clock":"01:20","description":"[ATL 45-51] Millsap Layup Shot: Made (18 PTS)","home_score":"51","visitor_score":"45","team_abr":"ATL"},{"event":"246","clock":"01:20","description":"[ATL] Millsap Rebound (Off:5 Def:2)","home_score":"51","visitor_score":"43","team_abr":"ATL"},{"event":"247","clock":"01:02","description":"[ORL] Ridnour Turnover : Lost Ball (2 TO) Steal:Carroll (2 ST)","home_score":"51","visitor_score":"45","team_abr":"ORL"},{"event":"248","clock":"00:55","description":"[ATL] Carroll 3pt Shot: Missed","home_score":"51","visitor_score":"45","team_abr":"ATL"},{"event":"249","clock":"00:54","description":"[ORL] Oladipo Rebound (Off:0 Def:3)","home_score":"51","visitor_score":"45","team_abr":"ORL"},{"event":"250","clock":"00:53","description":"[ATL] Horford Foul: Personal (2 PF)","home_score":"51","visitor_score":"45","team_abr":"ATL"},{"event":"251","clock":"00:36","description":"[ATL] Millsap Foul: Shooting (1 PF) (2 FTA)","home_score":"51","visitor_score":"45","team_abr":"ATL"},{"event":"252","clock":"00:36","description":"[ORL] Harris Free Throw 1 of 2 Missed","home_score":"51","visitor_score":"45","team_abr":"ORL"},{"event":"253","clock":"00:36","description":"[ORL] Team Rebound","home_score":"51","visitor_score":"45","team_abr":"ORL"},{"event":"254","clock":"00:36","description":"[ORL] Ridnour Substitution replaced by Green","home_score":"51","visitor_score":"45","team_abr":"ORL"},{"event":"255","clock":"00:36","description":"[ORL 52-45] Harris Free Throw 2 of 2 (10 PTS)","home_score":"52","visitor_score":"45","team_abr":"ORL"},{"event":"257","clock":"00:31","description":"[ATL 47-52] Horford Dunk Shot: Made (6 PTS) Assist: Teague (3 AST)","home_score":"52","visitor_score":"47","team_abr":"ATL"},{"event":"258","clock":"00:29","description":"[ORL] Team Timeout : Short","home_score":"52","visitor_score":"47","team_abr":"ORL"},{"event":"259","clock":"00:29","description":"[ATL] Horford Substitution replaced by Antic","home_score":"52","visitor_score":"47","team_abr":"ATL"},{"event":"260","clock":"00:29","description":"[ORL] Dedmon Substitution replaced by Ridnour","home_score":"52","visitor_score":"47","team_abr":"ORL"},{"event":"261","clock":"00:07","description":"[ORL] Ridnour 3pt Shot: Missed","home_score":"52","visitor_score":"47","team_abr":"ORL"},{"event":"262","clock":"00:06","description":"[ATL] Millsap Rebound (Off:5 Def:3)","home_score":"52","visitor_score":"47","team_abr":"ATL"},{"event":"263","clock":"00:00","description":"[ATL] Korver 3pt Shot: Missed","home_score":"52","visitor_score":"47","team_abr":"ATL"},{"event":"264","clock":"00:00","description":"[ATL] Team Rebound","home_score":"52","visitor_score":"47","team_abr":"ATL"},{"event":"265","clock":"00:00","description":"End Period","home_score":"52","visitor_score":"47","team_abr":""}]}}}